lmsleepdata/__init__.py
lmsleepdata/datahandler.py
lmsleepdata/predict_with_sleepyco_net.py
lmsleepdata/data_download/__init__.py
lmsleepdata/data_download/data_download.py
lmsleepdata/data_load/__init__.py
lmsleepdata/data_load/data_loader.py
lmsleepdata/data_load/loaders.py
lmsleepdata/function_in_test/__init__.py
lmsleepdata/function_in_test/other_features.py
lmsleepdata/function_in_test/realtime_sleep_analyse_test.py
lmsleepdata/functions/__init__.py
lmsleepdata/functions/biomarker.py
lmsleepdata/functions/feature_extract.py
lmsleepdata/functions/os_detect.py
lmsleepdata/functions/posture_analyse.py
lmsleepdata/functions/sleep_staging.py
lmsleepdata/functions/sleep_variable_compute.py
lmsleepdata/functions/spindle_detect.py
lmsleepdata/functions/wear_detect.py
lmsleepdata/models/realtime_sleep_staging.txt
lmsleepdata/models/sleepyco_people_model.pth
lmsleepdata/models/wear_detection_1s.txt
lmsleepdata/models/wear_detection_1s_v1.txt
lmsleepdata/models/wear_detection_1s_v2.txt
lmsleepdata/models/wholenight_acc_sleep_staging_v1.txt
lmsleepdata/models/wholenight_acc_sleep_staging_v2.txt
lmsleepdata/models/wholenight_acc_sleep_staging_v3.txt
lmsleepdata/models/wholenight_acc_sleep_staging_v4.txt
lmsleepdata/models/wholenight_acc_sleep_staging_v5.txt
lmsleepdata/models/wholenight_acc_sleep_staging_v6.txt
lmsleepdata/models/wholenight_acc_sleep_staging_v7.txt
lmsleepdata/models/wholenight_sleep_staging.txt
lmsleepdata/models/wholenight_sleep_staging_v1.txt
lmsleepdata/others/msyhbd.ttc
lmsleepdata/pdf/__init__.py
lmsleepdata/pdf/pdf_generator.py
lmsleepdata/plots/__init__.py
lmsleepdata/plots/cluster_plot.py
lmsleepdata/plots/metrics_plot.py
lmsleepdata/plots/rsp_contrast_plot.py
lmsleepdata/plots/sleep_staging_plot.py
lmsleepdata/plots/stim_plot.py
lmsleepdata/postprocess/__init__.py
lmsleepdata/postprocess/label_smooth.py
lmsleepdata/preprocess/__init__.py
lmsleepdata/preprocess/filter.py
lmsleepdata/preprocess/tailor.py
lmsleepdata/scripts/__init__.py
lmsleepdata-0.2.2.3.dist-info/LICENSE
lmsleepdata-0.2.2.3.dist-info/METADATA
lmsleepdata-0.2.2.3.dist-info/WHEEL
lmsleepdata-0.2.2.3.dist-info/top_level.txt
lmsleepdata-0.2.2.3.dist-info/RECORD
