Metadata-Version: 2.1
Name: lmsleepdata
Version: 0.2.2.3
Summary: a python analyse tool for LM Data Recorder data
Home-page: https://github.com/eegion/lmsleepdata
Author: quanlan
Author-email: dev@eegion.com
License: MIT License
Keywords: eeg sleep staging analysis
Platform: any
License-File: LICENSE
Requires-Dist: scipy (>=1.10.1)
Requires-Dist: matplotlib (>=3.3.4)
Requires-Dist: seaborn (>=0.12.2)
Requires-Dist: numpy (>=1.23.5)
Requires-Dist: numba (==0.56.4)
Requires-Dist: pandas (>=2.0.2)
Requires-Dist: mne (==1.4.0)
Requires-Dist: scikit-learn (>=1.2.2)
Requires-Dist: lightgbm (==3.3.5)
Requires-Dist: antropy (==0.1.4)
Requires-Dist: lspopt (>=1.3.0)
Requires-Dist: openpyxl (>=3.1.2)
Requires-Dist: reportlab (>=4.0.4)
Requires-Dist: pillow (>=10.0.0)
Requires-Dist: redis (>=3.5.3)
